anuga-3.2.0.data/scripts/anuga_benchmark_omp
anuga-3.2.0.data/scripts/anuga_pmesh_gui
anuga-3.2.0.data/scripts/anuga_sww_merge
anuga.libs/libgomp-5b4f3667.so.1.0.0
anuga/__init__.py
anuga/__metadata__.py
anuga/abstract_2d_finite_volumes/__init__.py
anuga/abstract_2d_finite_volumes/ermapper_grids.py
anuga/abstract_2d_finite_volumes/file_function.py
anuga/abstract_2d_finite_volumes/gauge.py
anuga/abstract_2d_finite_volumes/general_mesh.py
anuga/abstract_2d_finite_volumes/generic_boundary_conditions.py
anuga/abstract_2d_finite_volumes/generic_domain.py
anuga/abstract_2d_finite_volumes/mesh_factory.py
anuga/abstract_2d_finite_volumes/mesh_factory_ext.cpython-310-x86_64-linux-gnu.so
anuga/abstract_2d_finite_volumes/neighbour_mesh.py
anuga/abstract_2d_finite_volumes/neighbour_mesh_ext.cpython-310-x86_64-linux-gnu.so
anuga/abstract_2d_finite_volumes/neighbour_table_ext.cpython-310-x86_64-linux-gnu.so
anuga/abstract_2d_finite_volumes/old_setup.py
anuga/abstract_2d_finite_volumes/pmesh2domain.py
anuga/abstract_2d_finite_volumes/pmesh2domain_ext.cpython-310-x86_64-linux-gnu.so
anuga/abstract_2d_finite_volumes/quantity.py
anuga/abstract_2d_finite_volumes/quantity_cuda_ext.cpython-310-x86_64-linux-gnu.so
anuga/abstract_2d_finite_volumes/quantity_openmp_ext.cpython-310-x86_64-linux-gnu.so
anuga/abstract_2d_finite_volumes/region.py
anuga/abstract_2d_finite_volumes/tag_region.py
anuga/abstract_2d_finite_volumes/tests/__init__.py
anuga/abstract_2d_finite_volumes/tests/show_balanced_limiters.py
anuga/abstract_2d_finite_volumes/tests/test_ermapper.py
anuga/abstract_2d_finite_volumes/tests/test_gauge.py
anuga/abstract_2d_finite_volumes/tests/test_general_mesh.py
anuga/abstract_2d_finite_volumes/tests/test_generic_boundary_conditions.py
anuga/abstract_2d_finite_volumes/tests/test_generic_domain.py
anuga/abstract_2d_finite_volumes/tests/test_ghost.py
anuga/abstract_2d_finite_volumes/tests/test_neighbour_mesh.py
anuga/abstract_2d_finite_volumes/tests/test_pmesh2domain.py
anuga-3.2.0.dist-info/METADATA
anuga-3.2.0.dist-info/WHEEL
anuga-3.2.0.dist-info/licenses/LICENSE.txt
anuga-3.2.0.dist-info/RECORD
