Metadata-Version: 2.4
Name: anuga
Version: 3.2.0
Summary: A set of python modules for tsunami and flood modelling
Author-Email: Stephen Roberts <stephen.roberts@anu.edu.au>
License-Expression: Apache-2.0
License-File: LICENSE.txt
Classifier: Intended Audience :: Science/Research
Classifier: Intended Audience :: Developers
Classifier: Programming Language :: C
Classifier: Programming Language :: C++
Classifier: Programming Language :: Python
Classifier: Topic :: Software Development
Classifier: Topic :: Scientific/Engineering
Classifier: Operating System :: Microsoft :: Windows
Classifier: Operating System :: POSIX
Classifier: Operating System :: Unix
Classifier: Operating System :: MacOS
Classifier: Programming Language :: Python :: 3.9
Classifier: Programming Language :: Python :: 3.10
Classifier: Programming Language :: Python :: 3.11
Classifier: Programming Language :: Python :: 3.12
Classifier: Programming Language :: Python :: 3.13
Project-URL: homepage, https://en.wikipedia.org/wiki/ANUGA_Hydro
Project-URL: documentation, https://anuga.readthedocs.io
Project-URL: source, https://github.com/anuga-community/anuga_core
Project-URL: download, https://github.com/anuga-community/anuga_core/releases
Project-URL: tracker, https://github.com/anuga-community/anuga_core/issues
Requires-Python: <3.14,>3.8
Requires-Dist: numpy>=2.0.0
